ptorru_matmul/__init__.py
ptorru_matmul-0.1.6.dist-info/LICENSE
ptorru_matmul-0.1.6.dist-info/WHEEL
ptorru_matmul-0.1.6.dist-info/METADATA
ptorru_matmul-0.1.6.dist-info/RECORD
